odam_sdk/__init__.py
odam_sdk/cli.py
odam_sdk/client.py
odam_sdk/config.py
odam_sdk/models.py
odam_sdk/utils.py
odam_sdk-2.0.0.dist-info/licenses/LICENSE
odam_sdk-2.0.0.dist-info/METADATA
odam_sdk-2.0.0.dist-info/WHEEL
odam_sdk-2.0.0.dist-info/entry_points.txt
odam_sdk-2.0.0.dist-info/top_level.txt
odam_sdk-2.0.0.dist-info/RECORD
