Metadata-Version: 2.4
Name: odam-sdk
Version: 2.0.0
Summary: Офіційний Python SDK для інтеграції з ODAM V4 - системою штучного інтелекту з людською пам'яттю
Home-page: https://api.odam.dev
Author: ODAM Technologies
Author-email: support@odam.dev
License: MIT
Project-URL: Bug Tracker, https://api.odam.dev/issues
Project-URL: Documentation, https://docs.odam.dev
Project-URL: Source Code, https://api.odam.dev
Project-URL: Website, https://odam.dev
Keywords: ai,artificial-intelligence,chatbot,nlp,natural-language-processing,memory,conversation,chat,api,sdk,machine-learning,deep-learning,neural-networks,language-model,text-generation,entity-extraction,knowledge-graph,semantic-search,vector-search,embeddings,medical-nlp,healthcare,multilingual,ukrainian,enterprise,saas,cloud,rest-api,fastapi,python,typescript,javascript,java,dotnet
Platform: any
Classifier: Development Status :: 5 - Production/Stable
Classifier: Intended Audience :: Developers
Classifier: License :: OSI Approved :: MIT License
Classifier: Operating System :: OS Independent
Classifier: Programming Language :: Python :: 3
Classifier: Programming Language :: Python :: 3.8
Classifier: Programming Language :: Python :: 3.9
Classifier: Programming Language :: Python :: 3.10
Classifier: Programming Language :: Python :: 3.11
Classifier: Programming Language :: Python :: 3.12
Classifier: Topic :: Software Development :: Libraries :: Python Modules
Classifier: Topic :: Scientific/Engineering :: Artificial Intelligence
Classifier: Topic :: Text Processing :: Linguistic
Classifier: Topic :: Communications :: Chat
Classifier: Topic :: Database
Classifier: Topic :: Internet :: WWW/HTTP :: HTTP Servers
Classifier: Topic :: Internet :: WWW/HTTP :: WSGI :: Application
Classifier: Topic :: Software Development :: Libraries :: Application Frameworks
Classifier: Topic :: System :: Distributed Computing
Classifier: Topic :: System :: Monitoring
Classifier: Topic :: System :: Networking :: Monitoring
Classifier: Topic :: System :: Systems Administration
Classifier: Topic :: Utilities
Requires-Python: >=3.8
License-File: LICENSE
Requires-Dist: requests>=2.31.0
Requires-Dist: pydantic>=2.0.0
Requires-Dist: pydantic-settings>=2.0.0
Requires-Dist: typing-extensions>=4.5.0
Requires-Dist: structlog>=23.1.0
Provides-Extra: dev
Requires-Dist: pytest>=7.0.0; extra == "dev"
Requires-Dist: pytest-cov>=4.0.0; extra == "dev"
Requires-Dist: pytest-asyncio>=0.21.0; extra == "dev"
Requires-Dist: black>=23.0.0; extra == "dev"
Requires-Dist: isort>=5.12.0; extra == "dev"
Requires-Dist: flake8>=6.0.0; extra == "dev"
Requires-Dist: mypy>=1.0.0; extra == "dev"
Requires-Dist: pre-commit>=3.0.0; extra == "dev"
Requires-Dist: sphinx>=6.0.0; extra == "dev"
Requires-Dist: sphinx-rtd-theme>=1.2.0; extra == "dev"
Provides-Extra: test
Requires-Dist: pytest>=7.0.0; extra == "test"
Requires-Dist: pytest-cov>=4.0.0; extra == "test"
Requires-Dist: pytest-asyncio>=0.21.0; extra == "test"
Requires-Dist: pytest-mock>=3.10.0; extra == "test"
Requires-Dist: responses>=0.23.0; extra == "test"
Requires-Dist: freezegun>=1.2.0; extra == "test"
Provides-Extra: docs
Requires-Dist: sphinx>=6.0.0; extra == "docs"
Requires-Dist: sphinx-rtd-theme>=1.2.0; extra == "docs"
Requires-Dist: sphinx-autodoc-typehints>=1.19.0; extra == "docs"
Requires-Dist: myst-parser>=1.0.0; extra == "docs"
Provides-Extra: examples
Requires-Dist: fastapi>=0.100.0; extra == "examples"
Requires-Dist: uvicorn>=0.23.0; extra == "examples"
Requires-Dist: streamlit>=1.25.0; extra == "examples"
Requires-Dist: gradio>=3.35.0; extra == "examples"
Requires-Dist: dash>=2.10.0; extra == "examples"
Requires-Dist: plotly>=5.15.0; extra == "examples"
Dynamic: author
Dynamic: author-email
Dynamic: classifier
Dynamic: description
Dynamic: description-content-type
Dynamic: home-page
Dynamic: keywords
Dynamic: license
Dynamic: license-file
Dynamic: platform
Dynamic: project-url
Dynamic: provides-extra
Dynamic: requires-dist
Dynamic: requires-python
Dynamic: summary
